{
    "mumbai": [
      { "id": 1, "name": "Chhatrapati Shivaji International Airport" },
      { "id": 2, "name": "Bandra Kurla Complex" },
      { "id": 3, "name": "Gateway of India" },
      { "id": 4, "name": "CSMT Railway Station" },
      { "id": 5, "name": "Juhu Beach" }
    ],
    "delhi": [
      { "id": 1, "name": "Indira Gandhi International Airport" },
      { "id": 2, "name": "Connaught Place" },
      { "id": 3, "name": "New Delhi Railway Station" },
      { "id": 4, "name": "India Gate" },
      { "id": 5, "name": "Chandni Chowk" }
    ],
    "bengaluru": [
      { "id": 1, "name": "Kempegowda International Airport" },
      { "id": 2, "name": "MG Road" },
      { "id": 3, "name": "Electronic City" },
      { "id": 4, "name": "Cubbon Park" },
      { "id": 5, "name": "Bangalore Palace" }
    ],
    "chennai": [
      { "id": 1, "name": "Chennai International Airport" },
      { "id": 2, "name": "Marina Beach" },
      { "id": 3, "name": "Central Railway Station" },
      { "id": 4, "name": "T. Nagar" },
      { "id": 5, "name": "Phoenix MarketCity" }
    ],
    "kolkata": [
      { "id": 1, "name": "Netaji Subhash Chandra Bose International Airport" },
      { "id": 2, "name": "Howrah Railway Station" },
      { "id": 3, "name": "Victoria Memorial" },
      { "id": 4, "name": "Salt Lake City" },
      { "id": 5, "name": "New Market" }
    ]
  }